tests/__init__.py
tests/server/__init__.py
tests_server/__init__.py
tests_server/test_cleanup.py
tests_server/test_hashedpassword.py
tests_server/test_models.py
tests_server/test_resources.py
vantage6/server/__build__
vantage6/server/__init__.py
vantage6/server/_version.py
vantage6/server/algo_store_communication.py
vantage6/server/db.py
vantage6/server/default_roles.py
vantage6/server/exceptions.py
vantage6/server/globals.py
vantage6/server/hashedpassword.py
vantage6/server/permission.py
vantage6/server/utils.py
vantage6/server/websockets.py
vantage6/server/wsgi.py
vantage6/server/_data/example_fixtures.yaml
vantage6/server/_data/unittest_config.yaml
vantage6/server/_data/unittest_fixtures.yaml
vantage6/server/cli/__init__.py
vantage6/server/cli/server.py
vantage6/server/controller/__init__.py
vantage6/server/controller/cleanup.py
vantage6/server/controller/fixture.py
vantage6/server/model/__init__.py
vantage6/server/model/algorithm_port.py
vantage6/server/model/algorithm_store.py
vantage6/server/model/authenticatable.py
vantage6/server/model/base.py
vantage6/server/model/collaboration.py
vantage6/server/model/member.py
vantage6/server/model/node.py
vantage6/server/model/node_config.py
vantage6/server/model/organization.py
vantage6/server/model/permission.py
vantage6/server/model/role.py
vantage6/server/model/role_rule_association.py
vantage6/server/model/rule.py
vantage6/server/model/run.py
vantage6/server/model/study.py
vantage6/server/model/task.py
vantage6/server/model/task_database.py
vantage6/server/model/user.py
vantage6/server/model/common/utils.py
vantage6/server/resource/__init__.py
vantage6/server/resource/algorithm_store.py
vantage6/server/resource/blobstream.py
vantage6/server/resource/collaboration.py
vantage6/server/resource/event.py
vantage6/server/resource/health.py
vantage6/server/resource/node.py
vantage6/server/resource/organization.py
vantage6/server/resource/port.py
vantage6/server/resource/recover.py
vantage6/server/resource/role.py
vantage6_server-4.13.6.dist-info/METADATA
vantage6_server-4.13.6.dist-info/WHEEL
vantage6_server-4.13.6.dist-info/entry_points.txt
vantage6_server-4.13.6.dist-info/top_level.txt
vantage6_server-4.13.6.dist-info/RECORD
