Metadata-Version: 2.4
Name: vantage6_server
Version: 4.13.6
Summary: Vantage6 server
Home-page: https://github.com/vantage6/vantage6
Requires-Python: >=3.10
Requires-Dist: bcrypt==4.0.1
Requires-Dist: flask==3.1.1
Requires-Dist: flask-cors==6.0.0
Requires-Dist: Flask-JWT-Extended==4.7.1
Requires-Dist: Flask-Principal==0.4.0
Requires-Dist: Flask-RESTful==0.3.10
Requires-Dist: flask-marshmallow==0.15.0
Requires-Dist: flask-socketio==5.5.1
Requires-Dist: gevent==25.4.2
Requires-Dist: ipython==8.10.0
Requires-Dist: kombu==5.2.4
Requires-Dist: marshmallow==3.26.2
Requires-Dist: pyjwt==2.9.0
Requires-Dist: pyotp==2.8.0
Requires-Dist: prometheus-client==0.21.1
Requires-Dist: requests==2.32.4
Requires-Dist: requests-oauthlib==1.3.1
Requires-Dist: schema==0.7.5
Requires-Dist: SQLAlchemy==1.4.46
Requires-Dist: werkzeug==3.1.5
Requires-Dist: vantage6==4.13.6
Requires-Dist: vantage6-common==4.13.6
Provides-Extra: dev
Requires-Dist: coverage==6.4.4; extra == "dev"
Requires-Dist: black; extra == "dev"
Requires-Dist: pre-commit; extra == "dev"
Dynamic: description
Dynamic: description-content-type
Dynamic: home-page
Dynamic: provides-extra
Dynamic: requires-dist
Dynamic: requires-python
Dynamic: summary
